capncord/__init__.py
capncord/abc.py
capncord/bot.py
capncord/channel.py
capncord/http.py
capncord/message.py
capncord/user.py
capncord.py-0.2.1.dist-info/LICENSE
capncord.py-0.2.1.dist-info/METADATA
capncord.py-0.2.1.dist-info/WHEEL
capncord.py-0.2.1.dist-info/top_level.txt
capncord.py-0.2.1.dist-info/RECORD
