Metadata-Version: 2.1
Name: capncord.py
Version: 0.2.1
Summary: A wrapper for the Capncord API.
Home-page: https://github.com/LyricLy/capncord.py
Author: LyricLy
Author-email: gulliverhanson@gmail.com
License: CC0
Keywords: wrapper,capncord,capncord.py
Platform: UNKNOWN
Classifier: Development Status :: 3 - Alpha
Classifier: License :: CC0 1.0 Universal (CC0 1.0) Public Domain Dedication
Classifier: Intended Audience :: Developers
Classifier: Natural Language :: English
Classifier: Operating System :: OS Independent
Classifier: Programming Language :: Python :: 3.5
Classifier: Programming Language :: Python :: 3.6
Classifier: Programming Language :: Python :: 3.7
Classifier: Programming Language :: Python :: 3 :: Only
Classifier: Topic :: Internet
Classifier: Topic :: Software Development :: Libraries
Classifier: Topic :: Software Development :: Libraries :: Python Modules
Classifier: Topic :: Utilities
Requires-Dist: aiohttp
Requires-Dist: websockets
